CHANGELOG.md
LICENSE
README.md
pyproject.toml
.github/workflows/pypi-publish.yml
landau/__init__.py
landau/_version.py
landau/calculate.py
landau/interpolate.py
landau/phases.py
landau/plot.py
landau/resample.py
landaupkg.egg-info/PKG-INFO
landaupkg.egg-info/SOURCES.txt
landaupkg.egg-info/dependency_links.txt
landaupkg.egg-info/requires.txt
landaupkg.egg-info/top_level.txt
notebooks/Basics.ipynb
notebooks/Toy.ipynb