Metadata-Version: 2.4
Name: landaupkg
Version: 1.3.1
Author-email: Marvin Poul <pmrv@posteo.de>
Project-URL: Repository, https://github.com/eisenforschung/landau
Classifier: Programming Language :: Python :: 3
Classifier: Operating System :: OS Independent
Requires-Python: <3.14,>=3.10
License-File: LICENSE
Requires-Dist: matplotlib<4,>=3
Requires-Dist: numpy<3,>1
Requires-Dist: pandas<3,>=2.2
Requires-Dist: scipy<2,>=1.11.0
Requires-Dist: shapely<=2.0.7,>1
Requires-Dist: seaborn<=0.13.2,>=0.12
Requires-Dist: scikit-learn<2,>=1.2
Provides-Extra: constraints
Requires-Dist: polyfit; extra == "constraints"
Dynamic: license-file
